spicytorch/__init__.py
spicytorch/cli.py
spicytorch-0.1.0.dist-info/METADATA
spicytorch-0.1.0.dist-info/WHEEL
spicytorch-0.1.0.dist-info/entry_points.txt
spicytorch-0.1.0.dist-info/top_level.txt
spicytorch-0.1.0.dist-info/RECORD
