Metadata-Version: 2.4
Name: spicytorch
Version: 0.1.0
Summary: 🌶️ Advanced PyTorch Components from Latest Research Papers - Spicing up your models!
Home-page: https://github.com/yourusername/spicytorch
Author: Your Name
Author-email: email@example.com
Keywords: pytorch,deep learning,activation functions,loss functions,optimizers,augmentation,research papers,neural networks
Classifier: Development Status :: 2 - Pre-Alpha
Classifier: Intended Audience :: Developers
Classifier: Intended Audience :: Science/Research
Classifier: Topic :: Scientific/Engineering :: Artificial Intelligence
Classifier: Topic :: Software Development :: Libraries :: Python Modules
Classifier: License :: OSI Approved :: MIT License
Classifier: Programming Language :: Python :: 3
Classifier: Programming Language :: Python :: 3.7
Classifier: Programming Language :: Python :: 3.8
Classifier: Programming Language :: Python :: 3.9
Classifier: Programming Language :: Python :: 3.10
Classifier: Programming Language :: Python :: 3.11
Requires-Python: >=3.7
Requires-Dist: click>=8.0.0
Requires-Dist: colorama>=0.4.4
Dynamic: author
Dynamic: author-email
Dynamic: classifier
Dynamic: description-content-type
Dynamic: home-page
Dynamic: keywords
Dynamic: requires-dist
Dynamic: requires-python
Dynamic: summary
